{
    "format_version": "1.12",
    "minecraft:recipe_shaped": {
        "description": {
            "identifier": "xp:ice_sword.recipe"
        },
        "tags": [ "crafting_table" ],
        "pattern": [
            "i",
            "N",
            "/"
        ],
        "key": {
            "i": { "item": "xp:ice_ingot" },
            "N": { "item": "xp:ice_ingot" },
            "/": { "item": "minecraft:stick" }
        },
        "result": {
            "item": "xp:ice_sword"
        }
    }
}