{
	"format_version": "1.12.0",
	"minecraft:geometry": [
		{
			"description": {
				"identifier": "geometry.shaday_armor_helmet",
				"texture_width": 128,
				"texture_height": 128,
				"visible_bounds_width": 3,
				"visible_bounds_height": 3,
				"visible_bounds_offset": [0, 1.5, 0]
			},
			"bones": [
				{
					"name": "root",
					"pivot": [0, 0, 0]
				},
				{
					"name": "waist",
					"parent": "root",
					"pivot": [0, 12, 0]
				},
				{
					"name": "body",
					"parent": "waist",
					"pivot": [0, 24, 0]
				},
				{
					"name": "head",
					"parent": "body",
					"pivot": [0, 24, 0]
				},
				{
					"name": "hat",
					"parent": "head",
					"pivot": [0, 23.5, 0],
					"cubes": [
						{
							"origin": [-4, 22, -4],
							"size": [8, 10, 8],
							"inflate": 0.6,
							"uv": {
								"north": {"uv": [11, 0], "uv_size": [8, 10]},
								"east": {"uv": [27, 0], "uv_size": [-8, 10]},
								"south": {"uv": [0, 16], "uv_size": [8, 10]},
								"west": {"uv": [19, 0], "uv_size": [8, 10]},
								"up": {"uv": [0, 26], "uv_size": [8, 8]}
							}
						},
						{
							"origin": [-1.5, 29.5, -5],
							"size": [3, 3, 1],
							"pivot": [0, 31, -1],
							"rotation": [0, 0, 45],
							"uv": {
								"north": {"uv": [8, 16], "uv_size": [3, 3]},
								"east": {"uv": [18, 20], "uv_size": [1, 3]},
								"south": {"uv": [11, 16], "uv_size": [-3, 3]},
								"west": {"uv": [10, 47], "uv_size": [1, 3]},
								"up": {"uv": [37, 46], "uv_size": [3, 1]},
								"down": {"uv": [53, 29], "uv_size": [3, -1]}
							}
						},
						{
							"origin": [-1.5, 30.5, -4.5],
							"size": [1, 3, 9],
							"pivot": [0, 32, 0],
							"rotation": [0, 0, 90],
							"uv": {
								"north": {"uv": [9, 52], "uv_size": [1, 3]},
								"east": {"uv": [45, 32], "uv_size": [9, 3]},
								"south": {"uv": [4, 53], "uv_size": [1, 3]},
								"up": {"uv": [41, 55], "uv_size": [1, 9]},
								"down": {"uv": [41, 64], "uv_size": [1, -9]}
							}
						},
						{
							"origin": [3.40992, 24.85865, -4.5],
							"size": [2, 1, 9],
							"inflate": 0.02,
							"pivot": [4.40992, 25.35865, 0],
							"rotation": [0, 0, 67.5],
							"uv": {
								"north": {"uv": [38, 65], "uv_size": [2, 1]},
								"south": {"uv": [65, 38], "uv_size": [2, 1]},
								"west": {"uv": [58, 7], "uv_size": [9, 1]},
								"up": {"uv": [20, 52], "uv_size": [2, 9]}
							}
						},
						{
							"origin": [-5.40992, 24.85865, -4.5],
							"size": [2, 1, 9],
							"inflate": 0.02,
							"pivot": [-4.40992, 25.35865, 0],
							"rotation": [0, 0, -67.5],
							"uv": {
								"north": {"uv": [40, 65], "uv_size": [-2, 1]},
								"east": {"uv": [67, 7], "uv_size": [-9, 1]},
								"south": {"uv": [67, 38], "uv_size": [-2, 1]},
								"up": {"uv": [22, 52], "uv_size": [-2, 9]}
							}
						},
						{
							"origin": [-1, 24.85865, -0.07008],
							"size": [2, 1, 9],
							"inflate": 0.02,
							"pivot": [0, 25.35865, 4.42992],
							"rotation": [-90, -22.5, 90],
							"uv": {
								"north": {"uv": [2, 68], "uv_size": [2, 1]},
								"south": {"uv": [2, 69], "uv_size": [2, 1]},
								"west": {"uv": [2, 70], "uv_size": [9, 1]},
								"up": {"uv": [0, 68], "uv_size": [2, 9]}
							}
						},
						{
							"origin": [5.27796, 29.93281, -0.78109],
							"size": [2, 1, 4],
							"inflate": -0.02,
							"pivot": [4.75, 30.43281, 1.72808],
							"rotation": [0, 0, 90],
							"uv": {
								"east": {"uv": [63, 21], "uv_size": [4, 1]},
								"south": {"uv": [65, 37], "uv_size": [2, 1]},
								"west": {"uv": [63, 22], "uv_size": [4, 1]},
								"up": {"uv": [58, 58], "uv_size": [2, 4]},
								"down": {"uv": [9, 63], "uv_size": [2, -4]}
							}
						},
						{
							"origin": [2.87856, 29.93281, -2.61438],
							"size": [2, 1, 2],
							"pivot": [4.75, 30.43281, 1.72808],
							"rotation": [0, -45, 90],
							"uv": {
								"north": {"uv": [65, 29], "uv_size": [2, 1]},
								"west": {"uv": [34, 65], "uv_size": [2, 1]},
								"up": {"uv": [63, 13], "uv_size": [2, 2]},
								"down": {"uv": [15, 65], "uv_size": [2, -2]}
							}
						},
						{
							"origin": [1.37923, 29.93281, -1.54767],
							"size": [2, 1, 3],
							"inflate": 0.02,
							"pivot": [4.75, 30.43281, 1.72808],
							"rotation": [0, -67.5, 90],
							"uv": {
								"east": {"uv": [64, 1], "uv_size": [3, 1]},
								"up": {"uv": [48, 59], "uv_size": [2, 3]},
								"down": {"uv": [0, 63], "uv_size": [2, -3]}
							}
						},
						{
							"origin": [2.53321, 29.93281, -0.8504],
							"size": [2, 1, 6],
							"pivot": [4.75, 30.43281, 1.72808],
							"rotation": [0, -22.5, 90],
							"uv": {
								"east": {"uv": [59, 55], "uv_size": [6, 1]},
								"west": {"uv": [59, 56], "uv_size": [6, 1]},
								"up": {"uv": [18, 55], "uv_size": [2, 6]},
								"down": {"uv": [34, 62], "uv_size": [2, -6]}
							}
						},
						{
							"origin": [0.78311, 29.93281, 2.59995],
							"size": [1.37421, 1, 1.37421],
							"inflate": 0.02,
							"pivot": [4.75, 30.43281, 1.72808],
							"rotation": [0, 22.5, 90],
							"uv": {
								"east": {"uv": [4, 56], "uv_size": [1, 1]},
								"south": {"uv": [60, 24], "uv_size": [1, 1]},
								"up": {"uv": [61, 15], "uv_size": [1, 1]},
								"down": {"uv": [61, 31], "uv_size": [1, -1]}
							}
						},
						{
							"origin": [-2.15732, 29.93281, 2.59995],
							"size": [1.37421, 1, 1.37421],
							"inflate": 0.02,
							"pivot": [-4.75, 30.43281, 1.72808],
							"rotation": [0, -22.5, -90],
							"uv": {
								"south": {"uv": [61, 24], "uv_size": [-1, 1]},
								"west": {"uv": [5, 56], "uv_size": [-1, 1]},
								"up": {"uv": [62, 15], "uv_size": [-1, 1]},
								"down": {"uv": [62, 31], "uv_size": [-1, -1]}
							}
						},
						{
							"origin": [-4.53321, 29.93281, -0.8504],
							"size": [2, 1, 6],
							"pivot": [-4.75, 30.43281, 1.72808],
							"rotation": [0, 22.5, -90],
							"uv": {
								"east": {"uv": [65, 56], "uv_size": [-6, 1]},
								"west": {"uv": [65, 55], "uv_size": [-6, 1]},
								"up": {"uv": [20, 55], "uv_size": [-2, 6]},
								"down": {"uv": [36, 62], "uv_size": [-2, -6]}
							}
						},
						{
							"origin": [-3.37923, 29.93281, -1.54767],
							"size": [2, 1, 3],
							"inflate": 0.02,
							"pivot": [-4.75, 30.43281, 1.72808],
							"rotation": [0, 67.5, -90],
							"uv": {
								"west": {"uv": [67, 1], "uv_size": [-3, 1]},
								"up": {"uv": [50, 59], "uv_size": [-2, 3]},
								"down": {"uv": [2, 63], "uv_size": [-2, -3]}
							}
						},
						{
							"origin": [-4.87856, 29.93281, -2.61438],
							"size": [2, 1, 2],
							"pivot": [-4.75, 30.43281, 1.72808],
							"rotation": [0, 45, -90],
							"uv": {
								"north": {"uv": [67, 29], "uv_size": [-2, 1]},
								"east": {"uv": [36, 65], "uv_size": [-2, 1]},
								"up": {"uv": [65, 13], "uv_size": [-2, 2]},
								"down": {"uv": [17, 65], "uv_size": [-2, -2]}
							}
						},
						{
							"origin": [-7.27796, 29.93281, -0.78109],
							"size": [2, 1, 4],
							"inflate": -0.02,
							"pivot": [-4.75, 30.43281, 1.72808],
							"rotation": [0, 0, -90],
							"uv": {
								"east": {"uv": [67, 22], "uv_size": [-4, 1]},
								"south": {"uv": [67, 37], "uv_size": [-2, 1]},
								"west": {"uv": [67, 21], "uv_size": [-4, 1]},
								"up": {"uv": [60, 58], "uv_size": [-2, 4]},
								"down": {"uv": [11, 63], "uv_size": [-2, -4]}
							}
						},
						{
							"origin": [-0.35816, 33.02593, -5.45241],
							"size": [2, 1, 3],
							"inflate": 0.02,
							"pivot": [2.75, 33.52593, -1.91404],
							"rotation": [0, -90, 90],
							"uv": {
								"east": {"uv": [5, 64], "uv_size": [3, 1]},
								"up": {"uv": [2, 60], "uv_size": [2, 3]},
								"down": {"uv": [60, 34], "uv_size": [2, -3]}
							}
						},
						{
							"origin": [1.75, 33.30576, -5.00206],
							"size": [2, 1, 6],
							"pivot": [2.75, 33.80576, -0.50206],
							"rotation": [0, -22.5, 90],
							"uv": {
								"east": {"uv": [59, 57], "uv_size": [6, 1]},
								"west": {"uv": [60, 23], "uv_size": [6, 1]},
								"up": {"uv": [51, 56], "uv_size": [2, 6]},
								"down": {"uv": [5, 63], "uv_size": [2, -6]}
							}
						},
						{
							"origin": [0.97579, 33.28133, -0.13862],
							"size": [1.37421, 1, 1.37421],
							"inflate": 0.02,
							"pivot": [2.75, 33.78133, -0.51218],
							"rotation": [0, 22.5, 90],
							"uv": {
								"east": {"uv": [14, 64], "uv_size": [1, 1]},
								"south": {"uv": [39, 64], "uv_size": [1, 1]},
								"up": {"uv": [14, 67], "uv_size": [1, 1]},
								"down": {"uv": [15, 68], "uv_size": [1, -1]}
							}
						},
						{
							"origin": [-1.64184, 33.02593, -5.45241],
							"size": [2, 1, 3],
							"inflate": 0.02,
							"pivot": [-2.75, 33.52593, -1.91404],
							"rotation": [0, 90, -90],
							"uv": {
								"west": {"uv": [8, 64], "uv_size": [-3, 1]},
								"up": {"uv": [4, 60], "uv_size": [-2, 3]},
								"down": {"uv": [62, 34], "uv_size": [-2, -3]}
							}
						},
						{
							"origin": [-3.75, 33.30576, -5.00206],
							"size": [2, 1, 6],
							"pivot": [-2.75, 33.80576, -0.50206],
							"rotation": [0, 22.5, -90],
							"uv": {
								"east": {"uv": [66, 23], "uv_size": [-6, 1]},
								"west": {"uv": [65, 57], "uv_size": [-6, 1]},
								"up": {"uv": [53, 56], "uv_size": [-2, 6]},
								"down": {"uv": [7, 63], "uv_size": [-2, -6]}
							}
						},
						{
							"origin": [-2.35, 33.28133, -0.13862],
							"size": [1.37421, 1, 1.37421],
							"inflate": 0.02,
							"pivot": [-2.75, 33.78133, -0.51218],
							"rotation": [0, -22.5, -90],
							"uv": {
								"south": {"uv": [40, 64], "uv_size": [-1, 1]},
								"west": {"uv": [15, 64], "uv_size": [-1, 1]},
								"up": {"uv": [15, 67], "uv_size": [-1, 1]},
								"down": {"uv": [16, 68], "uv_size": [-1, -1]}
							}
						}
					]
				},
				{
					"name": "bone",
					"parent": "hat",
					"pivot": [5.96715, 29.80355, 13.20289]
				}
			]
		}
	]
}